spinesTS/__init__.py
spinesTS/features_generator.py
spinesTS/frame.py
spinesTS/metrics.py
spinesTS/pipeline.py
spinesTS/base/__init__.py
spinesTS/base/_base_mixin.py
spinesTS/base/_torch_mixin.py
spinesTS/data/__init__.py
spinesTS/data/_data_generator.py
spinesTS/data/_data_reader.py
spinesTS/data/built-in-datasets/AirPassengers.csv
spinesTS/data/built-in-datasets/ETTh1.csv
spinesTS/data/built-in-datasets/ETTh2.csv
spinesTS/data/built-in-datasets/ETTm1.csv
spinesTS/data/built-in-datasets/ETTm2.csv
spinesTS/data/built-in-datasets/Electric_Production.csv
spinesTS/data/built-in-datasets/M3_monthly_FTS.csv
spinesTS/data/built-in-datasets/M3_monthly_TSTS.csv
spinesTS/data/built-in-datasets/M3_other_FTS .csv
spinesTS/data/built-in-datasets/M3_other_TSTS.csv
spinesTS/data/built-in-datasets/M3_quarterly_FTS.csv
spinesTS/data/built-in-datasets/M3_quarterly_TSTS.csv
spinesTS/data/built-in-datasets/M3_yearly_FTS.csv
spinesTS/data/built-in-datasets/M3_yearly_TSTS.csv
spinesTS/data/built-in-datasets/Messages_Sent.csv
spinesTS/data/built-in-datasets/Messages_Sent_Hour.csv
spinesTS/data/built-in-datasets/Supermarket_Incoming.csv
spinesTS/data/built-in-datasets/Web_Sales.csv
spinesTS/data/built-in-datasets/metadata.yaml
spinesTS/layers/__init__.py
spinesTS/layers/_concat_layers.py
spinesTS/layers/_decompose_layers.py
spinesTS/layers/_enhance_layers.py
spinesTS/layers/_multi_features.py
spinesTS/layers/_position_encoder.py
spinesTS/ml_model/__init__.py
spinesTS/ml_model/_dummy_model.py
spinesTS/ml_model/_gbrt.py
spinesTS/ml_model/_io_model.py
spinesTS/ml_model/_multistep_forecast.py
spinesTS/nn/__init__.py
spinesTS/nn/_gau.py
spinesTS/nn/_patch_rnn.py
spinesTS/nn/_rnn.py
spinesTS/nn/_seg_rnn.py
spinesTS/nn/_tcn.py
spinesTS/nn/_time2vec_net.py
spinesTS/nn/utils/__init__.py
spinesTS/nn/utils/weight_norm.py
spinesTS/plotting/__init__.py
spinesTS/plotting/_plot_base.py
spinesTS/preprocessing/__init__.py
spinesTS/preprocessing/_denoise.py
spinesTS/preprocessing/_interpolate.py
spinesTS-0.4.11.dist-info/LICENSE
spinesTS-0.4.11.dist-info/METADATA
spinesTS-0.4.11.dist-info/WHEEL
spinesTS-0.4.11.dist-info/top_level.txt
spinesTS-0.4.11.dist-info/RECORD
