Metadata-Version: 2.1
Name: spinesTS
Version: 0.4.11
Summary: spinesTS, a powerful timeseries toolsets.
Home-page: https://github.com/BirchKwok/spinesTS
Author: Birch Kwok
Author-email: birchkwok@gmail.com
Keywords: machine learning
Classifier: License :: OSI Approved :: Apache Software License
Classifier: Operating System :: OS Independent
Classifier: Programming Language :: Python :: 3.9
Classifier: Programming Language :: Python :: 3.10
Classifier: Programming Language :: Python :: 3.11
License-File: LICENSE
Requires-Dist: scikit-learn >=1.0.2
Requires-Dist: torch >=2.0.0
Requires-Dist: scipy >=1.7.0
Requires-Dist: numpy >=1.17.0
Requires-Dist: pandas >=2.0.0
Requires-Dist: tabulate >=0.8
Requires-Dist: matplotlib >=3.5.1
Requires-Dist: spinesUtils >=0.3.13
